pyspark_eda/__init__.py
pyspark_eda/bivariate_analysis.py
pyspark_eda/multivariate_analysis.py
pyspark_eda/univariate_analysis.py
pyspark_eda/utils.py
pyspark_eda-1.6.0.dist-info/METADATA
pyspark_eda-1.6.0.dist-info/WHEEL
pyspark_eda-1.6.0.dist-info/top_level.txt
pyspark_eda-1.6.0.dist-info/RECORD
