Metadata-Version: 2.1
Name: pyspark_eda
Version: 1.6.0
Summary: A Python package for univariate ,bivariate and multivariate data analysis using PySpark
Author: Tanya Irani
Author-email: tanyairani22@gmail.com.com
Keywords: data analysis pyspark univariate bivariate mutlivariate statistics
Requires-Python: >=3.6
Requires-Dist: pyspark >=3.0.0
Requires-Dist: matplotlib >=3.0.0
Requires-Dist: scipy >=1.4.0
Requires-Dist: seaborn >=0.11.0
